odoo/addons/ssi_psychology_evaluation_operating_unit/README.rst
odoo/addons/ssi_psychology_evaluation_operating_unit/__init__.py
odoo/addons/ssi_psychology_evaluation_operating_unit/__manifest__.py
odoo/addons/ssi_psychology_evaluation_operating_unit/models/__init__.py
odoo/addons/ssi_psychology_evaluation_operating_unit/models/psychology_evaluation.py
odoo/addons/ssi_psychology_evaluation_operating_unit/models/psychology_evaluation_batch.py
odoo/addons/ssi_psychology_evaluation_operating_unit/security/ir_rule_data.xml
odoo/addons/ssi_psychology_evaluation_operating_unit/security/res_group_data.xml
odoo/addons/ssi_psychology_evaluation_operating_unit/static/description/icon.png
odoo/addons/ssi_psychology_evaluation_operating_unit/views/psychology_evaluation_batch_views.xml
odoo/addons/ssi_psychology_evaluation_operating_unit/views/psychology_evaluation_views.xml
odoo14_addon_ssi_psychology_evaluation_operating_unit-14.0.1.2.0.dist-info/METADATA
odoo14_addon_ssi_psychology_evaluation_operating_unit-14.0.1.2.0.dist-info/WHEEL
odoo14_addon_ssi_psychology_evaluation_operating_unit-14.0.1.2.0.dist-info/top_level.txt
odoo14_addon_ssi_psychology_evaluation_operating_unit-14.0.1.2.0.dist-info/RECORD
